coranking/__init__.py
coranking/_coranking.py
coranking/_metrics_cy.cpython-39-darwin.so
coranking/metrics.py
coranking/test/__init__.py
coranking/test/metrics_test.py
pycoranking-0.1.6.dist-info/LICENSE.txt
pycoranking-0.1.6.dist-info/METADATA
pycoranking-0.1.6.dist-info/WHEEL
pycoranking-0.1.6.dist-info/top_level.txt
pycoranking-0.1.6.dist-info/RECORD
