Metadata-Version: 2.1
Name: pycoranking
Version: 0.1.6
Summary: Co-ranking matrices for Python
Home-page: http://github.com/samueljackson92/coranking
Author: Samuel Jackson
Author-email: samueljackson@outlook.com
License: UNKNOWN
Download-URL: http://github.com/samueljackson92/coranking
Platform: UNKNOWN
Requires-Dist: numpy
Requires-Dist: scipy
